README.rst
setup.py
headless_pdfkit/__init__.py
headless_pdfkit.egg-info/PKG-INFO
headless_pdfkit.egg-info/SOURCES.txt
headless_pdfkit.egg-info/dependency_links.txt
headless_pdfkit.egg-info/not-zip-safe
headless_pdfkit.egg-info/requires.txt
headless_pdfkit.egg-info/top_level.txt