Metadata-Version: 1.0
Name: headless-pdfkit
Version: 0.1.5
Summary: A headless version of pdfkit which makes use of xvfb-run
Home-page: http://github.com/mrshu/headless_pdfkit
Author: Marek Suppa (mr.Shu)
Author-email: mr@shu.io
License: MIT
Platform: UNKNOWN
